india_map_corrector/__init__.py
india_map_corrector/core.py
india_map_corrector/dynamic.py
india_map_corrector/plotly_viz.py
india_map_corrector/static.py
india_map_corrector/styles.py
india_map_corrector/wrappers.py
india_map_corrector/data/world_corrected.geojson
india_map_corrector-0.1.0.dist-info/licenses/LICENSE
india_map_corrector-0.1.0.dist-info/METADATA
india_map_corrector-0.1.0.dist-info/WHEEL
india_map_corrector-0.1.0.dist-info/top_level.txt
india_map_corrector-0.1.0.dist-info/RECORD
