Metadata-Version: 2.4
Name: india-map-corrector
Version: 0.1.0
Summary: Python module to visualize maps with correct (de jure) India borders
Author-email: Your Name <your.email@example.com>
Keywords: india,map,geojson,visualization,borders,folium,plotly,matplotlib
Classifier: Development Status :: 3 - Alpha
Classifier: Intended Audience :: Developers
Classifier: Intended Audience :: Science/Research
Classifier: License :: OSI Approved :: MIT License
Classifier: Programming Language :: Python :: 3
Classifier: Programming Language :: Python :: 3.10
Classifier: Programming Language :: Python :: 3.11
Classifier: Programming Language :: Python :: 3.12
Classifier: Programming Language :: Python :: 3.13
Classifier: Topic :: Scientific/Engineering :: GIS
Classifier: Topic :: Scientific/Engineering :: Visualization
Requires-Python: >=3.10
License-File: LICENSE
Requires-Dist: folium>=0.20.0
Requires-Dist: geopandas>=1.0.0
Requires-Dist: matplotlib>=3.8.0
Requires-Dist: plotly>=5.18.0
Requires-Dist: pandas>=2.0.0
Requires-Dist: numpy>=1.24.0
Requires-Dist: nbformat>=5.10.4
Provides-Extra: dev
Requires-Dist: pytest>=7.0.0; extra == "dev"
Requires-Dist: jupyter>=1.0.0; extra == "dev"
Dynamic: license-file
